iceberg_mcp/__init__.py
iceberg_mcp/iceberg_config.py
iceberg_mcp/iceberg_server.py
iceberg_mcp_fastmcp-0.1.9.dist-info/METADATA
iceberg_mcp_fastmcp-0.1.9.dist-info/WHEEL
iceberg_mcp_fastmcp-0.1.9.dist-info/entry_points.txt
iceberg_mcp_fastmcp-0.1.9.dist-info/licenses/LICENSE
iceberg_mcp_fastmcp-0.1.9.dist-info/RECORD
