Metadata-Version: 2.4
Name: iceberg-mcp-fastmcp
Version: 0.1.9
Summary: An MCP server that interacts with Iceberg tables.
Project-URL: Homepage, https://github.com/fastmcp-me/iceberg-mcp#readme
Project-URL: Repository, https://github.com/fastmcp-me/iceberg-mcp.git
Project-URL: Issues, https://github.com/fastmcp-me/iceberg-mcp/issues
License-Expression: Apache-2.0
License-File: LICENSE
Requires-Python: >=3.11
Requires-Dist: httpx>=0.28.1
Requires-Dist: ipython>=8.32.0
Requires-Dist: mcp[cli]>=1.3.0
Requires-Dist: pyarrow>=19.0.1
Requires-Dist: pyiceberg[glue,s3fs]>=0.9.0
